scuba/__init__.py
scuba/__main__.py
scuba/argcomplete_stub.py
scuba/config.py
scuba/constants.py
scuba/dockerutil.py
scuba/scuba.py
scuba/scubainit
scuba/utils.py
scuba/version.py
scuba-2.14.2.dist-info/licenses/LICENSE.txt
scuba-2.14.2.dist-info/METADATA
scuba-2.14.2.dist-info/WHEEL
scuba-2.14.2.dist-info/entry_points.txt
scuba-2.14.2.dist-info/top_level.txt
scuba-2.14.2.dist-info/RECORD
