Metadata-Version: 2.4
Name: scuba
Version: 2.14.2
Summary: Simplify use of Docker containers for building software
Author-email: Jonathon Reinhart <jonathon.reinhart@gmail.com>
License: The MIT License (MIT)
Project-URL: documentation, https://scuba.readthedocs.io/
Project-URL: repository, https://github.com/JonathonReinhart/scuba
Project-URL: changelog, https://github.com/JonathonReinhart/scuba/blob/main/CHANGELOG.md
Keywords: docker
Classifier: Development Status :: 5 - Production/Stable
Classifier: Environment :: Console
Classifier: Intended Audience :: Developers
Classifier: License :: OSI Approved :: MIT License
Classifier: Natural Language :: English
Classifier: Operating System :: POSIX :: Linux
Classifier: Operating System :: MacOS :: MacOS X
Classifier: Topic :: Software Development :: Build Tools
Requires-Python: >=3.9
License-File: LICENSE.txt
Requires-Dist: PyYAML
Provides-Extra: argcomplete
Requires-Dist: argcomplete>=1.10.1; extra == "argcomplete"
Dynamic: license-file
